{
	"ident": 1022,
	"order": 16387,
	"objtype": "kLabel",
	"properties": {
		"align": "kLeftJst",
		"backcolor": "kColorBackFill",
		"backpattern": 15,
		"designactive": true,
		"edgefloat": "kEFnone",
		"fieldstyle": "CtrlLabel",
		"font": 5,
		"fontsize": 0,
		"fontstyle": "kPlain",
		"forecolor": "kColorForeFill",
		"height": 19,
		"left": 266,
		"objlink": 0,
		"text": "Severity",
		"textcolor": "kColorWindowText",
		"top": 10,
		"userinfo": "",
		"vertcentertext": false,
		"visible": true,
		"width": 120
	}
}
